{"Task": 355, "Sample": 3, "Model_type": "irr", "Name_of_run": "neuro_new1", "Combination_name": "latest_github_neuro_new_neuro_new1", "Objective": 0.0, "Termination_condition": "optimal", "Solution_is_feasible": true, "Solution_respects_SV_constraints": true, "Newly_created_model_is_feasible": true, "Root_work_units": 0, "Optimization_work_units": 0.01, "Time": 1.2233669757843018, "Expressionless_reaction_value": 1.14, "Epsilon": 0.0001, "Unbounded_lower_bound_value": 1, "Unbounded_upper_bound_value": 1000, "Solver_settings": {"TimeLimit": 2200}, "Transformation": "NT", "Thresholding": "NT", "GPR_method": "min2Sum", "Promiscuity_method": "N", "Tasklist": "neuro_new1", "Model_version": "latest_github", "Expression_dataset": "neuro_new", "Reactions": ["temporary_exchange_MAM02519[e]_f", "temporary_exchange_MAM02519[e]_r", "temporary_exchange_MAM01280[e]_f", "temporary_exchange_MAM01280[e]_r"], "Reaction_fluxes": [0.0, 0.0, 0.0, 0.0], "Reaction_expression": [-1, -1, -1, -1], "Reaction_objective_penalties": [0, 0, 0, 0], "Reaction_names": ["temporary_exchange_MAM02519[e]_f", "temporary_exchange_MAM02519[e]_r", "temporary_exchange_MAM01280[e]_f", "temporary_exchange_MAM01280[e]_r"], "Reaction_formulas": [" --> MAM02519[e]", "MAM02519[e] --> ", " --> MAM01280[e]", "MAM01280[e] --> "], "Converted_formulas": [" --> Na+[e]", "Na+[e] --> ", " --> adenosine[e]", "adenosine[e] --> "], "Version_of_code": "1.0.0", "Optimization values": [1, 1, 1, 1], "Contributing_gene_per_reaction": [{}, {}, {}, {}], "Date": "2025-06-06 16:50:34"}